knito/__init__.py
knito/myfuncs.py
pylib/__init__.py
pylib/myfuncs.py
knito-0.1.5.dist-info/LICENSE
knito-0.1.5.dist-info/METADATA
knito-0.1.5.dist-info/WHEEL
knito-0.1.5.dist-info/top_level.txt
knito-0.1.5.dist-info/RECORD
