Metadata-Version: 2.1
Name: knito
Version: 0.1.5
Summary: Magic with strings.
Home-page: https://github.com/Humungus-Fungus/Knito
Author: HumFung
Author-email: devarshdinesh@gmail.com
License: MIT
Keywords: strings
Platform: UNKNOWN
Classifier: Development Status :: 3 - Alpha
Classifier: Intended Audience :: Developers
Classifier: Topic :: Software Development :: Build Tools
Classifier: License :: OSI Approved :: MIT License
Classifier: Programming Language :: Python :: 3.6
